googletv/__init__.py
googletv/constants.py
googletv/device.py
googletv/exception.py
googletv/search.py
googletv-0.0.3.dist-info/LICENSE
googletv-0.0.3.dist-info/WHEEL
googletv-0.0.3.dist-info/METADATA
googletv-0.0.3.dist-info/RECORD
