Metadata-Version: 2.1
Name: googletv
Version: 0.0.3
Summary: 
License: MIT
Author: Sören Oldag
Author-email: soeren_oldag@freenet.de
Requires-Python: >=3.10
Classifier: License :: OSI Approved :: MIT License
Classifier: Programming Language :: Python :: 3
Classifier: Programming Language :: Python :: 3.10
Classifier: Programming Language :: Python :: 3.11
Requires-Dist: adb-shell[async] (>=0.4.3,<0.5.0)
